eokulapi/EokulAPI.py
eokulapi/Models/Absenteeism.py
eokulapi/Models/AbsenteeismContainer.py
eokulapi/Models/AdditionalExam.py
eokulapi/Models/AvgMark.py
eokulapi/Models/AvgMarkContainer.py
eokulapi/Models/AvgMarkLesson.py
eokulapi/Models/Document.py
eokulapi/Models/DocumentContainer.py
eokulapi/Models/EndtermMark.py
eokulapi/Models/EndtermMarkContainer.py
eokulapi/Models/EokulDictable.py
eokulapi/Models/EokulStudent.py
eokulapi/Models/ExamSchedule.py
eokulapi/Models/ExamScheduleContainer.py
eokulapi/Models/Lesson.py
eokulapi/Models/LessonDay.py
eokulapi/Models/LessonSchedule.py
eokulapi/Models/MarkContainer.py
eokulapi/Models/MarkLesson.py
eokulapi/Models/Responsibility.py
eokulapi/Models/Transfer.py
eokulapi/Models/__init__.py
eokulapi/__init__.py
eokulapi-0.0.17.dist-info/LICENSE
eokulapi-0.0.17.dist-info/METADATA
eokulapi-0.0.17.dist-info/WHEEL
eokulapi-0.0.17.dist-info/RECORD
